comando_teste/__init__.py
comando_teste/main.py
comando_teste-0.1.0.dist-info/entry_points.txt
comando_teste-0.1.0.dist-info/METADATA
comando_teste-0.1.0.dist-info/WHEEL
comando_teste-0.1.0.dist-info/RECORD
