Metadata-Version: 2.1
Name: comando-teste
Version: 0.1.0
Summary: 
Author: Daniel Rodrigues
Author-email: daniel.neves.rodrigues@devoteam.com
Requires-Python: >=3.11,<4.0
Classifier: Programming Language :: Python :: 3
Classifier: Programming Language :: Python :: 3.11
Requires-Dist: typer[all] (>=0.7.0,<0.8.0)
